[
  { "_id": "A101", "title": "Propulsion Assignment", "course": "RS101" },
  { "_id": "A102", "title": "Combustion Analysis", "course": "RS101" },
  { "_id": "A103", "title": "Nozzle Design Project", "course": "RS101" },
  { "_id": "A104", "title": "Rocket Engine Types Comparison", "course": "RS101" },
  { "_id": "A105", "title": "Fuel Chemistry Lab Report", "course": "RS101" },
  { "_id": "A201", "title": "Aerodynamics Quiz", "course": "RS102" },
  { "_id": "A202", "title": "Flow Analysis", "course": "RS102" },
  { "_id": "A203", "title": "Heating Analysis", "course": "RS102" },
  { "_id": "A204", "title": "Airfoil Design Challenge", "course": "RS102" },
  { "_id": "A205", "title": "Wind Tunnel Lab", "course": "RS102" },
  { "_id": "A301", "title": "Structural Design Task", "course": "RS103" },
  { "_id": "A302", "title": "Orbital Calculations", "course": "RS103" },
  { "_id": "A303", "title": "Systems Engineering Exam", "course": "RS103" },
  { "_id": "A304", "title": "Mission Planning Project", "course": "RS103" },
  { "_id": "A305", "title": "Thermal Control System Design", "course": "RS103" },
  { "_id": "A401", "title": "Organic Synthesis Lab", "course": "RS104" },
  { "_id": "A402", "title": "Spectroscopy Assignment", "course": "RS104" },
  { "_id": "A403", "title": "Stereochemistry Problem Set", "course": "RS104" },
  { "_id": "A404", "title": "Organic Chemistry Midterm", "course": "RS104" },
  { "_id": "A501", "title": "Coordination Complex Synthesis", "course": "RS105" },
  { "_id": "A502", "title": "Crystal Field Theory Analysis", "course": "RS105" },
  { "_id": "A503", "title": "Bonding Theories Comparison", "course": "RS105" },
  { "_id": "A504", "title": "Catalysis Research Project", "course": "RS105" },
  { "_id": "A601", "title": "Thermodynamics Problem Set", "course": "RS106" },
  { "_id": "A602", "title": "Kinetics Lab Report", "course": "RS106" },
  { "_id": "A603", "title": "Quantum Mechanics Assignment", "course": "RS106" },
  { "_id": "A604", "title": "Spectroscopy and Molecular Structure", "course": "RS106" },
  { "_id": "A701", "title": "Elvish Translation Project", "course": "RS107" },
  { "_id": "A702", "title": "Dwarvish Runes Analysis", "course": "RS107" },
  { "_id": "A703", "title": "Comparative Linguistics Essay", "course": "RS107" },
  { "_id": "A704", "title": "Black Speech Etymology", "course": "RS107" },
  { "_id": "A801", "title": "Council of Elrond Analysis", "course": "RS108" },
  { "_id": "A802", "title": "Alliance Formation Case Study", "course": "RS108" },
  { "_id": "A803", "title": "War of the Ring Diplomacy", "course": "RS108" },
  { "_id": "A804", "title": "Leadership Styles Comparison", "course": "RS108" },
  { "_id": "A805", "title": "Conflict Resolution Simulation", "course": "RS108" }
]